MANIFEST.in
README.rst
setup.py
GetGrowth.egg-info/PKG-INFO
GetGrowth.egg-info/SOURCES.txt
GetGrowth.egg-info/dependency_links.txt
GetGrowth.egg-info/not-zip-safe
GetGrowth.egg-info/requires.txt
GetGrowth.egg-info/top_level.txt
getgrowth/__init__.py
getgrowth/__main__.py
getgrowth/biolector.csv
getgrowth/engine.py
getgrowth/gui.glade
getgrowth/gui.py
getgrowth/my.py
getgrowth.egg-info/SOURCES.txt
getgrowth/docs/manual.pdf