Metadata-Version: 1.0
Name: getgrowth
Version: 0.2.7
Summary: Determining growth rates from Biolector experiments
Home-page: http://github.com/rasmusagren/getgrowth
Author: Rasmus Agren
Author-email: rasmus@alembic.se
License: GNU General Public License v2.0
Platform: UNKNOWN
